pytest_astropy/__init__.py
pytest_astropy/plugin.py
pytest_astropy/version.py
pytest_astropy-0.11.0.dist-info/LICENSE.rst
pytest_astropy-0.11.0.dist-info/METADATA
pytest_astropy-0.11.0.dist-info/WHEEL
pytest_astropy-0.11.0.dist-info/entry_points.txt
pytest_astropy-0.11.0.dist-info/top_level.txt
pytest_astropy-0.11.0.dist-info/RECORD
