Metadata-Version: 2.1
Name: pytest-astropy
Version: 0.11.0
Summary: Meta-package containing dependencies for testing
Home-page: https://github.com/astropy/pytest-astropy
Author: The Astropy Developers
Author-email: astropy.team@gmail.com
License: BSD
Keywords: pytest,remotedata,doctestplus,hypothesis,property-based testing
Classifier: Development Status :: 5 - Production/Stable
Classifier: Framework :: Pytest
Classifier: Framework :: Hypothesis
Classifier: Intended Audience :: Developers
Classifier: License :: OSI Approved :: BSD License
Classifier: Operating System :: OS Independent
Classifier: Programming Language :: Python
Classifier: Programming Language :: Python :: 3
Classifier: Programming Language :: Python :: 3 :: Only
Classifier: Programming Language :: Python :: 3.7
Classifier: Programming Language :: Python :: 3.8
Classifier: Programming Language :: Python :: Implementation :: CPython
Classifier: Topic :: Software Development :: Testing
Classifier: Topic :: Utilities
Requires-Python: >=3.7
License-File: LICENSE.rst
Requires-Dist: pytest>=4.6
Requires-Dist: pytest-doctestplus>=1.0.0
Requires-Dist: pytest-remotedata>=0.4.1
Requires-Dist: pytest-astropy-header>=0.2.2
Requires-Dist: pytest-arraydiff>=0.5
Requires-Dist: pytest-filter-subpackage>=0.1.2
Requires-Dist: pytest-cov>=2.3.1
Requires-Dist: pytest-mock>=2.0
Requires-Dist: attrs>=19.2.0
Requires-Dist: hypothesis>=5.1
